{"sections":{"main":{"type":"product-information","blocks":{"media-gallery":{"type":"_product-media-gallery","static":true,"settings":{"media_presentation":"grid","media_columns":"one","image_gap":0,"large_first_image":false,"icons_style":"arrow","slideshow_controls_style":"counter","slideshow_mobile_controls_style":"counter","thumbnail_position":"left","thumbnail_width":57,"aspect_ratio":"1\/1.25","constrain_to_viewport":false,"media_fit":"cover","media_radius":0,"extend_media":true,"zoom":true,"video_loop":false,"hide_variants":true,"padding-block-start":0,"padding-block-end":0,"padding-inline-start":0,"padding-inline-end":0},"blocks":{}},"product-details":{"type":"_product-details","static":true,"settings":{"width":"fill","custom_width":100,"width_mobile":"fill","custom_width_mobile":100,"height":"fit","details_position":"flex-start","gap":12,"sticky_details_desktop":true,"inherit_color_scheme":true,"color_scheme":"","background_media":"none","video_position":"cover","background_image_position":"cover","border":"none","border_width":1,"border_opacity":100,"border_radius":0,"padding-block-start":0,"padding-block-end":0,"padding-inline-start":0,"padding-inline-end":0},"blocks":{"heading_m7KmQQ":{"type":"text","settings":{"text":"<h1>{{ closest.product.title }}<\/h1>","width":"100%","max_width":"normal","alignment":"left","type_preset":"custom","font":"var(--font-heading--family)","font_size":"var(--font-size--h2)","line_height":"tight","letter_spacing":"normal","case":"none","wrap":"pretty","color":"","background":false,"background_color":"#00000026","corner_radius":0,"padding-block-start":40,"padding-block-end":0,"padding-inline-start":0,"padding-inline-end":0},"blocks":{}},"price_a7krng":{"type":"price","settings":{"show_sale_price_first":true,"show_installments":false,"show_tax_info":false,"type_preset":"h5","width":"100%","alignment":"left","font":"var(--font-body--family)","font_size":"1rem","line_height":"normal","letter_spacing":"normal","case":"none","color":"var(--color-primary)","padding-block-start":8,"padding-block-end":32,"padding-inline-start":0,"padding-inline-end":0},"blocks":{}},"divider_HrJgFt":{"type":"_divider","name":"t:names.divider","settings":{"thickness":1,"corner_radius":"square","width_percent":100,"padding-block-start":0,"padding-block-end":0},"blocks":{}},"variant_picker_R3rGDr":{"type":"variant-picker","settings":{"variant_style":"buttons","show_swatches":true,"alignment":"left","padding-block-start":24,"padding-block-end":24,"padding-inline-start":0,"padding-inline-end":0},"blocks":{}},"buy_buttons_eYQEYi":{"type":"buy-buttons","settings":{"stacking":false,"show_pickup_availability":false,"padding-block-start":0,"padding-block-end":32,"padding-inline-start":0,"padding-inline-end":0},"blocks":{"quantity":{"type":"quantity","disabled":true,"static":true,"settings":{},"blocks":{}},"add-to-cart":{"type":"add-to-cart","static":true,"settings":{"style_class":"button"},"blocks":{}},"accelerated-checkout":{"type":"accelerated-checkout","disabled":true,"static":true,"settings":{},"blocks":{}}},"block_order":[]},"trust_line_tm":{"type":"text","settings":{"text":"<p>Envío en 48–72h · Devoluciones en 14 días<\/p>","width":"100%","max_width":"normal","alignment":"center","type_preset":"custom","font":"var(--font-body--family)","font_size":"0.5625rem","line_height":"normal","letter_spacing":"0.08em","case":"none","wrap":"pretty","color":"","background":false,"background_color":"#00000026","corner_radius":0,"padding-block-start":0,"padding-block-end":0,"padding-inline-start":0,"padding-inline-end":0},"blocks":{}},"accordion_NKWPiW":{"type":"accordion","name":"t:names.accordion","settings":{"icon":"caret","dividers":true,"type_preset":"h6","inherit_color_scheme":true,"color_scheme":"","border":"none","border_width":1,"border_opacity":100,"border_radius":0,"padding-block-start":0,"padding-block-end":0,"padding-inline-start":0,"padding-inline-end":0},"blocks":{"accordion_row_NdBezV":{"type":"_accordion-row","settings":{"heading":"Descripción","open_by_default":false,"icon":"none","width":20},"blocks":{"text_n7A9da":{"type":"custom-liquid","settings":{"custom_liquid":"{{ product.description }}"},"blocks":{}}},"block_order":["text_n7A9da"]},"accordion_row_iJM37V":{"type":"_accordion-row","settings":{"heading":"Cuidados del lavado","open_by_default":false,"icon":"washing","width":20},"blocks":{"text_VdG98J":{"type":"text","settings":{"text":"<ul><li>Lavar del revés y en agua fría (máx. 30 °C)<\/li><li>No usar secadora<\/li><li>Planchar del revés, sin tocar el diseño<\/li><li>No usar lejía ni suavizantes agresivos<\/li><li>Evitar remojos prolongados o fricción sobre el estampado<\/li><\/ul>","width":"100%","max_width":"normal","alignment":"left","type_preset":"custom","font":"var(--font-body--family)","font_size":"0.875rem","line_height":"normal","letter_spacing":"normal","case":"none","wrap":"pretty","color":"","background":false,"background_color":"#00000026","corner_radius":0,"padding-block-start":12,"padding-block-end":0,"padding-inline-start":0,"padding-inline-end":0},"blocks":{}}},"block_order":["text_VdG98J"]},"accordion_row_pLFDcD":{"type":"_accordion-row","settings":{"heading":"Envío","open_by_default":false,"icon":"truck","width":20},"blocks":{"text_qLGEN9":{"type":"text","settings":{"text":"<ul><li>Envío desde 24\/48 horas<\/li><\/ul>","width":"100%","max_width":"normal","alignment":"left","type_preset":"custom","font":"var(--font-body--family)","font_size":"0.875rem","line_height":"normal","letter_spacing":"normal","case":"none","wrap":"pretty","color":"","background":false,"background_color":"#00000026","corner_radius":0,"padding-block-start":12,"padding-block-end":0,"padding-inline-start":0,"padding-inline-end":0},"blocks":{}}},"block_order":["text_qLGEN9"]}},"block_order":["accordion_row_NdBezV","accordion_row_iJM37V","accordion_row_pLFDcD"]}},"block_order":["heading_m7KmQQ","price_a7krng","divider_HrJgFt","variant_picker_R3rGDr","buy_buttons_eYQEYi","trust_line_tm","accordion_NKWPiW"]}},"settings":{"content_width":"content-full-width","desktop_media_position":"left","equal_columns":true,"limit_details_width":true,"gap":0,"enable_sticky_add_to_cart":false,"color_scheme":"scheme-5","padding-block-start":0,"padding-block-end":0}}},"order":["main"]}
